{
  "slug": "labrador-retriever-vs-poodle",
  "breed_a": {
    "name": "Labrador Retriever",
    "slug": "labrador-retriever",
    "group": "Sporting",
    "size": "large",
    "weight_min_kg": 25,
    "weight_max_kg": 36,
    "height_min_cm": 54,
    "height_max_cm": 62,
    "lifespan_min": 10,
    "lifespan_max": 12,
    "temperament": [
      "friendly",
      "outgoing",
      "active",
      "gentle"
    ],
    "health_issues": [
      "hip-dysplasia",
      "elbow-dysplasia",
      "obesity",
      "exercise-induced-collapse",
      "progressive-retinal-atrophy"
    ],
    "exercise_level": 4,
    "grooming_level": 2,
    "shedding_level": 4,
    "trainability": 5,
    "good_with_children": true,
    "good_with_dogs": true,
    "apartment_friendly": false,
    "popularity_rank": 1,
    "origin": "Canada",
    "coat_type": "short double",
    "coat_colors": [
      "yellow",
      "black",
      "chocolate"
    ],
    "description": "The Labrador Retriever has been the most popular dog breed in the United States for decades, beloved for its even temperament and versatility as a family companion, service dog, and sporting partner. Originally bred in Newfoundland to retrieve waterfowl for fishermen, Labs retain an enthusiastic love of water and an eager-to-please work ethic. Their intelligence and trainability make them the most widely used breed for guide, therapy, and detection work worldwide."
  },
  "breed_b": {
    "name": "Poodle",
    "slug": "poodle",
    "group": "Non-Sporting",
    "size": "medium",
    "weight_min_kg": 20,
    "weight_max_kg": 32,
    "height_min_cm": 38,
    "height_max_cm": 60,
    "lifespan_min": 10,
    "lifespan_max": 18,
    "temperament": [
      "intelligent",
      "active",
      "alert",
      "instinctual",
      "trainable"
    ],
    "health_issues": [
      "hip-dysplasia",
      "progressive-retinal-atrophy",
      "epilepsy",
      "sebaceous-adenitis",
      "addisons-disease"
    ],
    "exercise_level": 4,
    "grooming_level": 5,
    "shedding_level": 1,
    "trainability": 5,
    "good_with_children": true,
    "good_with_dogs": true,
    "apartment_friendly": true,
    "popularity_rank": 5,
    "origin": "Germany",
    "coat_type": "curly single",
    "coat_colors": [
      "apricot",
      "black",
      "white",
      "chocolate",
      "silver",
      "cream",
      "red"
    ],
    "description": "Despite its glamorous reputation, the Poodle was originally bred in Germany as a skilled water retriever, and its iconic show clips were designed to protect joints while swimming in cold water. Consistently ranked among the top two most intelligent dog breeds, Poodles come in Standard, Miniature, and Toy sizes and excel at virtually every canine sport. Their low-shedding coat makes them a popular choice for allergy sufferers, though regular professional grooming every six to eight weeks is essential to prevent matting."
  },
  "differences": [
    {
      "category": "Min Lifespan (years)",
      "breed_a_value": 10,
      "breed_b_value": 10,
      "winner": "tie"
    },
    {
      "category": "Max Lifespan (years)",
      "breed_a_value": 12,
      "breed_b_value": 18,
      "winner": "poodle"
    },
    {
      "category": "Min Weight (kg)",
      "breed_a_value": 25,
      "breed_b_value": 20,
      "winner": "tie"
    },
    {
      "category": "Max Weight (kg)",
      "breed_a_value": 36,
      "breed_b_value": 32,
      "winner": "tie"
    },
    {
      "category": "Min Height (cm)",
      "breed_a_value": 54,
      "breed_b_value": 38,
      "winner": "tie"
    },
    {
      "category": "Max Height (cm)",
      "breed_a_value": 62,
      "breed_b_value": 60,
      "winner": "tie"
    },
    {
      "category": "Exercise Level",
      "breed_a_value": 4,
      "breed_b_value": 4,
      "winner": "tie"
    },
    {
      "category": "Grooming Level",
      "breed_a_value": 2,
      "breed_b_value": 5,
      "winner": "tie"
    },
    {
      "category": "Shedding Level",
      "breed_a_value": 4,
      "breed_b_value": 1,
      "winner": "poodle"
    },
    {
      "category": "Trainability",
      "breed_a_value": 5,
      "breed_b_value": 5,
      "winner": "tie"
    },
    {
      "category": "Good with Children",
      "breed_a_value": true,
      "breed_b_value": true,
      "winner": "tie"
    },
    {
      "category": "Good with Dogs",
      "breed_a_value": true,
      "breed_b_value": true,
      "winner": "tie"
    },
    {
      "category": "Apartment Friendly",
      "breed_a_value": false,
      "breed_b_value": true,
      "winner": "poodle"
    },
    {
      "category": "Number of Common Health Issues",
      "breed_a_value": 5,
      "breed_b_value": 5,
      "winner": "tie"
    }
  ]
}